pyData/__init__.py
pyData/dataframe.py
pyData/json.py
pyStat/__init__.py
pySpotfireExt-0.0.1.dist-info/METADATA
pySpotfireExt-0.0.1.dist-info/WHEEL
pySpotfireExt-0.0.1.dist-info/top_level.txt
pySpotfireExt-0.0.1.dist-info/RECORD
