Metadata-Version: 2.1
Name: pySpotfireExt
Version: 0.0.1
Summary: python customized extend code.
Home-page: http://git.ksrnet.synology.me/ksr8308/python/03.dist/pySpotfireExt
Author: 
Author-email: 
Classifier: Programming Language :: Python :: 3
Classifier: License :: OSI Approved :: MIT License
Classifier: Operating System :: OS Independent
Requires-Python: >=3.8
